LICENSE.txt
MANIFEST.in
Pipfile
README.md
setup.py
mblibs/__init__.py
mblibs/fast.py
mblibs.egg-info/PKG-INFO
mblibs.egg-info/SOURCES.txt
mblibs.egg-info/dependency_links.txt
mblibs.egg-info/requires.txt
mblibs.egg-info/top_level.txt