Metadata-Version: 2.2
Name: mblibs
Version: 1.1.3
Summary: Fast tools for programming
Home-page: https://github.com/mickbad/mblibs
Author: MickBad
Author-email: prog@mickbad.com
License: MIT
Keywords: development tools fasting
Classifier: Programming Language :: Python
Classifier: Development Status :: 4 - Beta
Classifier: License :: OSI Approved :: GNU General Public License v3 (GPLv3)
Classifier: Natural Language :: French
Classifier: Operating System :: OS Independent
Classifier: Programming Language :: Python :: 3.5
Classifier: Programming Language :: Python :: 3.6
Classifier: Topic :: Software Development :: Libraries :: Application Frameworks
Classifier: Topic :: Software Development :: Libraries
Classifier: Topic :: Software Development :: Testing
Classifier: Topic :: Utilities
License-File: LICENSE.txt
Requires-Dist: pyyaml
Requires-Dist: python-dateutil
Dynamic: author
Dynamic: author-email
Dynamic: classifier
Dynamic: description
Dynamic: description-content-type
Dynamic: home-page
Dynamic: keywords
Dynamic: license
Dynamic: requires-dist
Dynamic: summary
